icalendar_anonymizer/__init__.py
icalendar_anonymizer/_hash.py
icalendar_anonymizer/_properties.py
icalendar_anonymizer/_version.py
icalendar_anonymizer/anonymizer.py
icalendar_anonymizer/cli.py
icalendar_anonymizer/version.py
icalendar_anonymizer/tests/__init__.py
icalendar_anonymizer/tests/cli/__init__.py
icalendar_anonymizer/tests/cli/test_cli.py
icalendar_anonymizer/tests/lib/__init__.py
icalendar_anonymizer/tests/lib/test_anonymization.py
icalendar_anonymizer/tests/lib/test_with_doctest.py
icalendar_anonymizer/tests/web/__init__.py
icalendar_anonymizer/tests/web/test_api.py
icalendar_anonymizer-0.1.1.dist-info/METADATA
icalendar_anonymizer-0.1.1.dist-info/WHEEL
icalendar_anonymizer-0.1.1.dist-info/entry_points.txt
icalendar_anonymizer-0.1.1.dist-info/licenses/LICENSE
icalendar_anonymizer-0.1.1.dist-info/RECORD
