Metadata-Version: 2.4
Name: icalendar-anonymizer
Version: 0.1.1
Summary: Strip personal data from iCalendar files while preserving technical properties for bug reproduction
Project-URL: Homepage, https://icalendar-anonymizer.readthedocs.io
Project-URL: Documentation, https://icalendar-anonymizer.readthedocs.io
Project-URL: Repository, https://github.com/mergecal/icalendar-anonymizer
Project-URL: Changelog, https://icalendar-anonymizer.readthedocs.io/stable/changelog.html
Project-URL: Issues, https://github.com/mergecal/icalendar-anonymizer/issues
Project-URL: Discussions, https://github.com/mergecal/icalendar-anonymizer/discussions
Project-URL: source_archive, https://github.com/mergecal/icalendar-anonymizer/archive/16f8e9c44fbf0f668d0a29d72a178d6c260a020a.zip
Author-email: Sashank Bhamidi <hello@sashank.wiki>, Nicco Kunzmann <niccokunzmann@rambler.ru>, Abe Hanoka <abe@habet.dev>
Maintainer-email: Sashank Bhamidi <hello@sashank.wiki>, Nicco Kunzmann <niccokunzmann@rambler.ru>, Abe Hanoka <abe@habet.dev>
License-Expression: AGPL-3.0-or-later
License-File: LICENSE
Keywords: anonymizer,calendar,icalendar,ics,privacy,vcalendar
Classifier: Development Status :: 3 - Alpha
Classifier: Intended Audience :: Developers
Classifier: License :: OSI Approved :: GNU Affero General Public License v3 or later (AGPLv3+)
Classifier: Operating System :: OS Independent
Classifier: Programming Language :: Python
Classifier: Programming Language :: Python :: 3
Classifier: Programming Language :: Python :: 3.11
Classifier: Programming Language :: Python :: 3.12
Classifier: Programming Language :: Python :: 3.13
Classifier: Programming Language :: Python :: Implementation :: CPython
Classifier: Topic :: Office/Business :: Scheduling
Classifier: Topic :: Software Development :: Libraries :: Python Modules
Requires-Python: >=3.11
Requires-Dist: icalendar>=6.3.0
Provides-Extra: all
Requires-Dist: build>=1.3; extra == 'all'
Requires-Dist: click>=8.3.1; extra == 'all'
Requires-Dist: commitizen>=4.10; extra == 'all'
Requires-Dist: coverage>=7.11; extra == 'all'
Requires-Dist: fastapi>=0.121.0; extra == 'all'
Requires-Dist: pre-commit>=4.4; extra == 'all'
Requires-Dist: pydata-sphinx-theme>=0.16.0; extra == 'all'
Requires-Dist: pytest-cov>=6.0; extra == 'all'
Requires-Dist: pytest>=9.0; extra == 'all'
Requires-Dist: reuse>=6.2; extra == 'all'
Requires-Dist: ruff>=0.14.0; extra == 'all'
Requires-Dist: sphinx-copybutton>=0.5.2; extra == 'all'
Requires-Dist: sphinx-design>=0.6.0; extra == 'all'
Requires-Dist: sphinx>=8.2; extra == 'all'
Requires-Dist: twine>=6.2; extra == 'all'
Requires-Dist: uvicorn[standard]>=0.38.0; extra == 'all'
Provides-Extra: cli
Requires-Dist: click>=8.3.1; extra == 'cli'
Provides-Extra: dev
Requires-Dist: build>=1.3; extra == 'dev'
Requires-Dist: commitizen>=4.10; extra == 'dev'
Requires-Dist: coverage>=7.11; extra == 'dev'
Requires-Dist: pre-commit>=4.4; extra == 'dev'
Requires-Dist: pytest-cov>=6.0; extra == 'dev'
Requires-Dist: pytest>=9.0; extra == 'dev'
Requires-Dist: reuse>=6.2; extra == 'dev'
Requires-Dist: ruff>=0.14.0; extra == 'dev'
Requires-Dist: twine>=6.2; extra == 'dev'
Provides-Extra: doc
Requires-Dist: pydata-sphinx-theme>=0.16.0; extra == 'doc'
Requires-Dist: sphinx-copybutton>=0.5.2; extra == 'doc'
Requires-Dist: sphinx-design>=0.6.0; extra == 'doc'
Requires-Dist: sphinx>=8.2; extra == 'doc'
Provides-Extra: test
Requires-Dist: click>=8.3.1; extra == 'test'
Requires-Dist: coverage>=7.11; extra == 'test'
Requires-Dist: hypothesis>=6.147; extra == 'test'
Requires-Dist: pytest-cov>=6.0; extra == 'test'
Requires-Dist: pytest>=9.0; extra == 'test'
Provides-Extra: web
Requires-Dist: fastapi>=0.121.0; extra == 'web'
Requires-Dist: uvicorn[standard]>=0.38.0; extra == 'web'
